[{"jaar":1701,"value":112946},{"jaar":1702,"value":87016},{"jaar":1703,"value":99889},{"jaar":1704,"value":60985},{"jaar":1707,"value":52383},{"jaar":1709,"value":86497},{"jaar":1711,"value":55134},{"jaar":1712,"value":69055},{"jaar":1713,"value":39452},{"jaar":1715,"value":76470},{"jaar":1722,"value":118985},{"jaar":1723,"value":120587},{"jaar":1724,"value":101936},{"jaar":1726,"value":105517},{"jaar":1727,"value":78544},{"jaar":1729,"value":75770},{"jaar":1731,"value":74335},{"jaar":1732,"value":62276},{"jaar":1735,"value":64387},{"jaar":1738,"value":58765},{"jaar":1739,"value":72235},{"jaar":1741,"value":64111},{"jaar":1742,"value":63758},{"jaar":1743,"value":56684},{"jaar":1751,"value":161626},{"jaar":1752,"value":156543},{"jaar":1753,"value":51346},{"jaar":1754,"value":20941},{"jaar":1755,"value":10580},{"jaar":1757,"value":133195},{"jaar":1759,"value":163133},{"jaar":1760,"value":43787},{"jaar":1761,"value":86488},{"jaar":1762,"value":32991},{"jaar":1763,"value":83948},{"jaar":1764,"value":57325},{"jaar":1766,"value":81907},{"jaar":1767,"value":63858},{"jaar":1769,"value":13375},{"jaar":1772,"value":30979},{"jaar":1773,"value":6296},{"jaar":1774,"value":11156},{"jaar":1775,"value":18838},{"jaar":1776,"value":13980},{"jaar":1777,"value":22792},{"jaar":1778,"value":49358},{"jaar":1779,"value":15845},{"jaar":1780,"value":38893},{"jaar":1781,"value":10710},{"jaar":1782,"value":2024},{"jaar":1783,"value":2054},{"jaar":1785,"value":61362},{"jaar":1787,"value":21684},{"jaar":1790,"value":10700}]
