[{"jaar":1701,"value":111},{"jaar":1702,"value":151},{"jaar":1703,"value":999},{"jaar":1704,"value":335},{"jaar":1707,"value":158},{"jaar":1709,"value":94},{"jaar":1711,"value":606},{"jaar":1712,"value":114},{"jaar":1713,"value":147},{"jaar":1715,"value":40},{"jaar":1722,"value":238},{"jaar":1723,"value":479},{"jaar":1724,"value":706},{"jaar":1726,"value":678},{"jaar":1727,"value":990},{"jaar":1729,"value":29},{"jaar":1731,"value":74},{"jaar":1732,"value":57},{"jaar":1742,"value":71},{"jaar":1743,"value":211},{"jaar":1753,"value":35},{"jaar":1759,"value":35},{"jaar":1760,"value":54},{"jaar":1761,"value":10},{"jaar":1762,"value":138},{"jaar":1767,"value":31},{"jaar":1774,"value":622},{"jaar":1775,"value":263},{"jaar":1776,"value":166},{"jaar":1778,"value":113},{"jaar":1780,"value":18},{"jaar":1781,"value":13},{"jaar":1785,"value":60},{"jaar":1787,"value":8}]
