[{"jaar":1701,"value":56784},{"jaar":1702,"value":35039},{"jaar":1703,"value":18487},{"jaar":1704,"value":21405},{"jaar":1707,"value":1455},{"jaar":1711,"value":65273},{"jaar":1712,"value":57990},{"jaar":1713,"value":12628},{"jaar":1715,"value":17246},{"jaar":1722,"value":15695},{"jaar":1723,"value":12468},{"jaar":1724,"value":6668},{"jaar":1726,"value":9868},{"jaar":1727,"value":5022},{"jaar":1729,"value":1910},{"jaar":1731,"value":1126},{"jaar":1732,"value":1723},{"jaar":1735,"value":1216},{"jaar":1738,"value":12122},{"jaar":1739,"value":5591},{"jaar":1741,"value":4218},{"jaar":1742,"value":6252},{"jaar":1743,"value":6592},{"jaar":1751,"value":21568},{"jaar":1752,"value":7421},{"jaar":1753,"value":16782},{"jaar":1754,"value":11447},{"jaar":1755,"value":4476},{"jaar":1757,"value":2154},{"jaar":1759,"value":11713},{"jaar":1760,"value":21055},{"jaar":1761,"value":4381},{"jaar":1764,"value":6727},{"jaar":1766,"value":12296},{"jaar":1767,"value":13356},{"jaar":1772,"value":403},{"jaar":1774,"value":204},{"jaar":1775,"value":1232},{"jaar":1776,"value":2341},{"jaar":1777,"value":1611},{"jaar":1778,"value":21347},{"jaar":1779,"value":18608},{"jaar":1780,"value":6272},{"jaar":1785,"value":11646}]
