[{"jaar":1701,"value":65826},{"jaar":1702,"value":103051},{"jaar":1703,"value":78285},{"jaar":1704,"value":156977},{"jaar":1707,"value":75179},{"jaar":1709,"value":179495},{"jaar":1711,"value":164646},{"jaar":1712,"value":97600},{"jaar":1713,"value":360003},{"jaar":1715,"value":197757},{"jaar":1722,"value":250831},{"jaar":1723,"value":159392},{"jaar":1724,"value":158902},{"jaar":1726,"value":190196},{"jaar":1727,"value":155755},{"jaar":1729,"value":123872},{"jaar":1731,"value":97318},{"jaar":1732,"value":89813},{"jaar":1735,"value":120696},{"jaar":1738,"value":191019},{"jaar":1739,"value":109481},{"jaar":1741,"value":55734},{"jaar":1742,"value":61785},{"jaar":1743,"value":58085},{"jaar":1751,"value":129960},{"jaar":1752,"value":65215},{"jaar":1753,"value":51406},{"jaar":1754,"value":48594},{"jaar":1755,"value":37571},{"jaar":1757,"value":171285},{"jaar":1759,"value":59235},{"jaar":1760,"value":103477},{"jaar":1761,"value":96754},{"jaar":1762,"value":26474},{"jaar":1763,"value":134193},{"jaar":1764,"value":63519},{"jaar":1766,"value":12074},{"jaar":1767,"value":32185},{"jaar":1769,"value":18169},{"jaar":1772,"value":45052},{"jaar":1773,"value":19798},{"jaar":1774,"value":6402},{"jaar":1775,"value":14904},{"jaar":1776,"value":19945},{"jaar":1777,"value":17210},{"jaar":1778,"value":29561},{"jaar":1779,"value":11818},{"jaar":1780,"value":23686},{"jaar":1781,"value":32518},{"jaar":1782,"value":6542},{"jaar":1783,"value":3741},{"jaar":1785,"value":4041},{"jaar":1790,"value":3340}]
