[{"jaar":1701,"value":395},{"jaar":1702,"value":546},{"jaar":1703,"value":81},{"jaar":1704,"value":227},{"jaar":1709,"value":512},{"jaar":1711,"value":91},{"jaar":1712,"value":374},{"jaar":1713,"value":259},{"jaar":1715,"value":171},{"jaar":1722,"value":10},{"jaar":1723,"value":561},{"jaar":1724,"value":644},{"jaar":1729,"value":2009},{"jaar":1731,"value":538},{"jaar":1738,"value":508},{"jaar":1739,"value":416},{"jaar":1741,"value":88},{"jaar":1742,"value":19},{"jaar":1751,"value":235},{"jaar":1752,"value":45},{"jaar":1753,"value":26},{"jaar":1757,"value":301},{"jaar":1760,"value":null},{"jaar":1764,"value":105},{"jaar":1767,"value":105},{"jaar":1769,"value":223},{"jaar":1781,"value":null}]
