[{"jaar":1703,"value":733},{"jaar":1713,"value":1604},{"jaar":1715,"value":3191},{"jaar":1722,"value":4912},{"jaar":1723,"value":175},{"jaar":1724,"value":3215},{"jaar":1726,"value":4562},{"jaar":1727,"value":5785},{"jaar":1729,"value":5222},{"jaar":1731,"value":1928},{"jaar":1732,"value":2359},{"jaar":1735,"value":5624},{"jaar":1738,"value":2587},{"jaar":1739,"value":1900},{"jaar":1752,"value":42871},{"jaar":1754,"value":1756},{"jaar":1757,"value":15473},{"jaar":1759,"value":24619},{"jaar":1761,"value":14284},{"jaar":1762,"value":954},{"jaar":1764,"value":98988},{"jaar":1780,"value":12838},{"jaar":1785,"value":9348}]
